Workbook

Sheet Trading History
K2: UnRealised | W2: Realised
K3: Total | O3: Short Term | S3: Long Term
A4: DATE | B4: EXCH | C4: ACTION | D4: Units | E4: NAV | F4: COST | G4: REMARKS | H4: STT | I4: ADDITIONAL CHARGES | J4: Current Price | K4: Gain % | L4: Gain | M4: Gross | N4: Units | O4: Gain % | P4: Gain | Q4: Gross | R4: Units | S4: Gain % | T4: Gain | U4: Gross | V4: Units | W4: Price | X4: Date | Y4: Gain % | Z4: Gain | AA4: Gross | AB4: Units
A5: 45849 | B5: NSE | C5: Buy | D5: =F5/E5 -> 290.89798 | E5: 17.1874 | F5: 4999.78 | G5: Online Sys. Investment (15/Perpetual) | J5: =Index!$C$2 -> 37.11 | K5: =IF(AND( C5="Buy", ISBLANK(W5), B5<>"DIV"), L5/sum(F5:I5), "") -> 1.1591398 | L5: =IF(AND( C5="Buy", ISBLANK(W5), B5<>"DIV"), (1-Index!$F$2*2)*((J5*D5)-(E5*D5)), "") -> 5795.4442 | M5: =IF(AND( C5="Buy", ISBLANK(W5), B5<>"DIV"), ((E5*D5)+L5), "") -> 10795.224 | N5: =IF(AND( C5="Buy", ISBLANK(W5), B5<>"DIV"), D5, "") -> 290.89798 | O5: =IF(AND( C5="Buy", ISBLANK(W5), B5<>"DIV", NOW()-A5 < 365, A5<TODAY()-365*Index!$J$1), P5/sum(F5:I5), "") -> 1.1591398 | P5: =IF(AND( C5="Buy", ISBLANK(W5), B5<>"DIV", NOW()-A5 < 365, A5<TODAY()-365*Index!$J$1), (1-Index!$F$2*2)*((J5*D5)-(E5*D5)), "") -> 5795.4442 | Q5: =IF(AND( C5="Buy", ISBLANK(W5), B5<>"DIV", NOW()-A5 < 365, A5<TODAY()-365*Index!$J$1), ((E5*D5)+P5), "") -> 10795.224 | R5: =IF(AND( C5="Buy", ISBLANK(W5), B5<>"DIV", NOW()-A5 < 365, A5<TODAY()-365*Index!$J$1), D5, "") -> 290.89798 | S5: =IF(AND( C5="Buy", ISBLANK(W5), B5<>"DIV", NOW()-A5 > 365, A5<TODAY()-365*Index!$J$1), T5/sum(F5:I5), "") | T5: =IF(AND( C5="Buy", ISBLANK(W5), B5<>"DIV", NOW()-A5 > 365, A5<TODAY()-365*Index!$J$1), (1-Index!$F$2*2)*((J5*D5)-(E5*D5)), "") | U5: =IF(AND( C5="Buy", ISBLANK(W5), B5<>"DIV", NOW()-A5 > 365, A5<TODAY()-365*Index!$J$1), ((E5*D5)+T5), "") | V5: =IF(AND( C5="Buy", ISBLANK(W5), B5<>"DIV", NOW()-A5 > 365, A5<TODAY()-365*Index!$J$1), D5, "")

Sheet Index
B1: Code | C1: MUTF_IN:NIPP_INDI_SILV_ACWJQM | I1: Lock In Period | J1: 0 | M1: =HYPERLINK(CONCATENATE("https://www.google.com/finance/quote/", #REF!, ":", #REF!, "?hl=en&window=1M"), "Google Finance Link") -> Google Finance Link
B2: Current Price | C2: =IFERROR(__xludf.DUMMYFUNCTION("GOOGLEFINANCE($C$1, ""price"")"),37.11) -> 37.11 | E2: Commission | F2: 0 | I2: Exit Load | J2: 0.08
B3: 52 Week High | C3: =IFERROR(__xludf.DUMMYFUNCTION("MAX(INDEX(GOOGLEFINANCE($C$1, ""price"", TODAY()-(366), TODAY()), ,2))"),56.4363) -> 56.4363
B4: 52 Week Low | C4: =IFERROR(__xludf.DUMMYFUNCTION("MIN(INDEX(GOOGLEFINANCE($C$1, ""price"", TODAY()-(366), TODAY()), ,2))"),14.0329) -> 14.0329
B6: UnRealised | K6: Realised
A8: All | B8: Units | C8: =SUM('Trading History'!$N$4:$N1003) -> 290.89798 | E8: ST Units | F8: =IFERROR(SUM('Trading History'!$R$4:$R1003), 0) -> 290.89798 | H8: LT Units | I8: =SUM('Trading History'!$V$4:$V1003) -> 0 | K8: Units | L8: =SUM('Trading History'!$AB$4:$AB1003) -> 0
B9: Avg % | C9: =IFERROR(Index!C10/(Index!C8*Index!$J$1), 0) -> 0 | E9: ST Avg % | F9: =IFERROR(Index!F10/(Index!F8*Index!$J$1), 0) -> 0 | H9: LT Avg % | I9: =IFERROR(Index!I10/(Index!I8*Index!$J$1), 0) -> 0 | K9: Avg % | L9: =IFERROR(Index!L10/(Index!L8*Index!$J$1), 0) -> 0
B10: Gain | C10: =SUM('Trading History'!$L$4:$L1003) -> 5795.4442 | E10: ST Gain | F10: =SUM('Trading History'!$P$4:$P1003) -> 5795.4442 | H10: LT Gain | I10: =SUM('Trading History'!$T$4:$T1003) -> 0 | K10: Gain | L10: =SUM('Trading History'!$Z$4:$Z1003) -> 0
B11: Invested | C11: =Index!C12-Index!C10 -> 4999.78 | E11: ST Invested | F11: =Index!F12-Index!F10 -> 4999.78 | H11: LT Invested | I11: =Index!I12-Index!I10 -> 0 | K11: Invested | L11: =Index!L12-Index!L10 -> 0
B12: Gross | C12: =SUM('Trading History'!$M$4:$M1003) -> 10795.224 | E12: ST Gross | F12: =SUM('Trading History'!$Q$4:$Q1003) -> 10795.224 | H12: LT Gross | I12: =SUM('Trading History'!$U$4:$U1003) -> 0 | K12: Gross | L12: =SUM('Trading History'!$AA$4:$AA1003) -> 0
K13: Dividends | L13: =SUMIF('Trading History'!$B6:$B1003,"DIV",#REF!) -> #N/A
A15: 0.5 | B15: Units | C15: =SUMIFS('Trading History'!$N$4:$N1003, 'Trading History'!$K$4:$K1003, CONCAT(">", $A15)) -> 290.89798 | E15: ST Units | F15: =IFERROR(SUMIFS('Trading History'!$R$4:$R1003, 'Trading History'!$O$4:$O1003, CONCAT(">", $A15)), 0) -> 290.89798 | H15: LT Units | I15: =SUMIFS('Trading History'!$V$4:$V1003, 'Trading History'!$S$4:$S1003, CONCAT(">", $A15)) -> 0 | K15: Units | L15: =SUMIFS('Trading History'!$AB$4:$AB1003, 'Trading History'!$Y$4:$Y1003, CONCAT(">", $A15)) -> 0
B16: Avg % | C16: =IFERROR(Index!C17/(Index!C15*Index!$J$1), 0) -> 0 | E16: ST Avg % | F16: =IFERROR(Index!F17/(Index!F15*Index!$J$1), 0) -> 0 | H16: LT Avg % | I16: =IFERROR(Index!I17/(Index!I15*Index!$J$1), 0) -> 0 | K16: Avg % | L16: =IFERROR(Index!L17/(Index!L15*Index!$J$1), 0) -> 0
B17: Gain | C17: =SUMIFS('Trading History'!$L$4:$L1003, 'Trading History'!$K$4:$K1003, CONCAT(">", $A15)) -> 5795.4442 | E17: ST Gain | F17: =SUMIFS('Trading History'!$P$4:$P1003, 'Trading History'!$O$4:$O1003, CONCAT(">", $A15)) -> 5795.4442 | H17: LT Gain | I17: =SUMIFS('Trading History'!$T$4:$T1003, 'Trading History'!$S$4:$S1003, CONCAT(">", $A15)) -> 0 | K17: Gain | L17: =SUMIFS('Trading History'!$Z$4:$Z1003, 'Trading History'!$Y$4:$Y1003, CONCAT(">", $A15)) -> 0
B18: Invested | C18: =Index!C19-Index!C17 -> 4999.78 | E18: ST Invested | F18: =Index!F19-Index!F17 -> 4999.78 | H18: LT Invested | I18: =Index!I19-Index!I17 -> 0 | K18: Invested | L18: =Index!L19-Index!L17 -> 0
B19: Gross | C19: =SUMIFS('Trading History'!$M$4:$M1003, 'Trading History'!$K$4:$K1003, CONCAT(">", $A15)) -> 10795.224 | E19: ST Gross | F19: =SUMIFS('Trading History'!$Q$4:$Q1003, 'Trading History'!$O$4:$O1003, CONCAT(">", $A15)) -> 10795.224 | H19: LT Gross | I19: =SUMIFS('Trading History'!$U$4:$U1003, 'Trading History'!$S$4:$S1003, CONCAT(">", $A15)) -> 0 | K19: Gross | L19: =SUMIFS('Trading History'!$AA$4:$AA1003, 'Trading History'!$Y$4:$Y1003, CONCAT(">", $A15)) -> 0
A22: 0.45 | B22: Units | C22: =SUMIFS('Trading History'!$N$4:$N1003, 'Trading History'!$K$4:$K1003, CONCAT(">", $A22)) -> 290.89798 | E22: ST Units | F22: =IFERROR(SUMIFS('Trading History'!$R$4:$R1003, 'Trading History'!$O$4:$O1003, CONCAT(">", $A22)), 0) -> 290.89798 | H22: LT Units | I22: =SUMIFS('Trading History'!$V$4:$V1003, 'Trading History'!$S$4:$S1003, CONCAT(">", $A22)) -> 0 | K22: Units | L22: =SUMIFS('Trading History'!$AB$4:$AB1003, 'Trading History'!$Y$4:$Y1003, CONCAT(">", $A22)) -> 0
B23: Avg % | C23: =IFERROR(Index!C24/(Index!C22*Index!$J$1), 0) -> 0 | E23: ST Avg % | F23: =IFERROR(Index!F24/(Index!F22*Index!$J$1), 0) -> 0 | H23: LT Avg % | I23: =IFERROR(Index!I24/(Index!I22*Index!$J$1), 0) -> 0 | K23: Avg % | L23: =IFERROR(Index!L24/(Index!L22*Index!$J$1), 0) -> 0
B24: Gain | C24: =SUMIFS('Trading History'!$L$4:$L1003, 'Trading History'!$K$4:$K1003, CONCAT(">", $A22)) -> 5795.4442 | E24: ST Gain | F24: =SUMIFS('Trading History'!$P$4:$P1003, 'Trading History'!$O$4:$O1003, CONCAT(">", $A22)) -> 5795.4442 | H24: LT Gain | I24: =SUMIFS('Trading History'!$T$4:$T1003, 'Trading History'!$S$4:$S1003, CONCAT(">", $A22)) -> 0 | K24: Gain | L24: =SUMIFS('Trading History'!$Z$4:$Z1003, 'Trading History'!$Y$4:$Y1003, CONCAT(">", $A22)) -> 0
B25: Invested | C25: =Index!C26-Index!C24 -> 4999.78 | E25: ST Invested | F25: =Index!F26-Index!F24 -> 4999.78 | H25: LT Invested | I25: =Index!I26-Index!I24 -> 0 | K25: Invested | L25: =Index!L26-Index!L24 -> 0
B26: Gross | C26: =SUMIFS('Trading History'!$M$4:$M1003, 'Trading History'!$K$4:$K1003, CONCAT(">", $A22)) -> 10795.224 | E26: ST Gross | F26: =SUMIFS('Trading History'!$Q$4:$Q1003, 'Trading History'!$O$4:$O1003, CONCAT(">", $A22)) -> 10795.224 | H26: LT Gross | I26: =SUMIFS('Trading History'!$U$4:$U1003, 'Trading History'!$S$4:$S1003, CONCAT(">", $A22)) -> 0 | K26: Gross | L26: =SUMIFS('Trading History'!$AA$4:$AA1003, 'Trading History'!$Y$4:$Y1003, CONCAT(">", $A22)) -> 0
A29: 0.4 | B29: Units | C29: =SUMIFS('Trading History'!$N$4:$N1003, 'Trading History'!$K$4:$K1003, CONCAT(">", $A29)) -> 290.89798 | E29: ST Units | F29: =IFERROR(SUMIFS('Trading History'!$R$4:$R1003, 'Trading History'!$O$4:$O1003, CONCAT(">", $A29)), 0) -> 290.89798 | H29: LT Units | I29: =SUMIFS('Trading History'!$V$4:$V1003, 'Trading History'!$S$4:$S1003, CONCAT(">", $A29)) -> 0 | K29: Units | L29: =SUMIFS('Trading History'!$AB$4:$AB1003, 'Trading History'!$Y$4:$Y1003, CONCAT(">", $A29)) -> 0
B30: Avg % | C30: =IFERROR(Index!C31/(Index!C29*Index!$J$1), 0) -> 0 | E30: ST Avg % | F30: =IFERROR(Index!F31/(Index!F29*Index!$J$1), 0) -> 0 | H30: LT Avg % | I30: =IFERROR(Index!I31/(Index!I29*Index!$J$1), 0) -> 0 | K30: Avg % | L30: =IFERROR(Index!L31/(Index!L29*Index!$J$1), 0) -> 0
B31: Gain | C31: =SUMIFS('Trading History'!$L$4:$L1003, 'Trading History'!$K$4:$K1003, CONCAT(">", $A29)) -> 5795.4442 | E31: ST Gain | F31: =SUMIFS('Trading History'!$P$4:$P1003, 'Trading History'!$O$4:$O1003, CONCAT(">", $A29)) -> 5795.4442 | H31: LT Gain | I31: =SUMIFS('Trading History'!$T$4:$T1003, 'Trading History'!$S$4:$S1003, CONCAT(">", $A29)) -> 0 | K31: Gain | L31: =SUMIFS('Trading History'!$Z$4:$Z1003, 'Trading History'!$Y$4:$Y1003, CONCAT(">", $A29)) -> 0
B32: Invested | C32: =Index!C33-Index!C31 -> 4999.78 | E32: ST Invested | F32: =Index!F33-Index!F31 -> 4999.78 | H32: LT Invested | I32: =Index!I33-Index!I31 -> 0 | K32: Invested | L32: =Index!L33-Index!L31 -> 0
B33: Gross | C33: =SUMIFS('Trading History'!$M$4:$M1003, 'Trading History'!$K$4:$K1003, CONCAT(">", $A29)) -> 10795.224 | E33: ST Gross | F33: =SUMIFS('Trading History'!$Q$4:$Q1003, 'Trading History'!$O$4:$O1003, CONCAT(">", $A29)) -> 10795.224 | H33: LT Gross | I33: =SUMIFS('Trading History'!$U$4:$U1003, 'Trading History'!$S$4:$S1003, CONCAT(">", $A29)) -> 0 | K33: Gross | L33: =SUMIFS('Trading History'!$AA$4:$AA1003, 'Trading History'!$Y$4:$Y1003, CONCAT(">", $A29)) -> 0
A36: 0.35 | B36: Units | C36: =SUMIFS('Trading History'!$N$4:$N1003, 'Trading History'!$K$4:$K1003, CONCAT(">", $A36)) -> 290.89798 | E36: ST Units | F36: =IFERROR(SUMIFS('Trading History'!$R$4:$R1003, 'Trading History'!$O$4:$O1003, CONCAT(">", $A36)), 0) -> 290.89798 | H36: LT Units | I36: =SUMIFS('Trading History'!$V$4:$V1003, 'Trading History'!$S$4:$S1003, CONCAT(">", $A36)) -> 0 | K36: Units | L36: =SUMIFS('Trading History'!$AB$4:$AB1003, 'Trading History'!$Y$4:$Y1003, CONCAT(">", $A36)) -> 0
B37: Avg % | C37: =IFERROR(Index!C38/(Index!C36*Index!$J$1), 0) -> 0 | E37: ST Avg % | F37: =IFERROR(Index!F38/(Index!F36*Index!$J$1), 0) -> 0 | H37: LT Avg % | I37: =IFERROR(Index!I38/(Index!I36*Index!$J$1), 0) -> 0 | K37: Avg % | L37: =IFERROR(Index!L38/(Index!L36*Index!$J$1), 0) -> 0
B38: Gain | C38: =SUMIFS('Trading History'!$L$4:$L1003, 'Trading History'!$K$4:$K1003, CONCAT(">", $A36)) -> 5795.4442 | E38: ST Gain | F38: =SUMIFS('Trading History'!$P$4:$P1003, 'Trading History'!$O$4:$O1003, CONCAT(">", $A36)) -> 5795.4442 | H38: LT Gain | I38: =SUMIFS('Trading History'!$T$4:$T1003, 'Trading History'!$S$4:$S1003, CONCAT(">", $A36)) -> 0 | K38: Gain | L38: =SUMIFS('Trading History'!$Z$4:$Z1003, 'Trading History'!$Y$4:$Y1003, CONCAT(">", $A36)) -> 0
B39: Invested | C39: =Index!C40-Index!C38 -> 4999.78 | E39: ST Invested | F39: =Index!F40-Index!F38 -> 4999.78 | H39: LT Invested | I39: =Index!I40-Index!I38 -> 0 | K39: Invested | L39: =Index!L40-Index!L38 -> 0
B40: Gross | C40: =SUMIFS('Trading History'!$M$4:$M1003, 'Trading History'!$K$4:$K1003, CONCAT(">", $A36)) -> 10795.224 | E40: ST Gross | F40: =SUMIFS('Trading History'!$Q$4:$Q1003, 'Trading History'!$O$4:$O1003, CONCAT(">", $A36)) -> 10795.224 | H40: LT Gross | I40: =SUMIFS('Trading History'!$U$4:$U1003, 'Trading History'!$S$4:$S1003, CONCAT(">", $A36)) -> 0 | K40: Gross | L40: =SUMIFS('Trading History'!$AA$4:$AA1003, 'Trading History'!$Y$4:$Y1003, CONCAT(">", $A36)) -> 0
A43: 0.3 | B43: Units | C43: =SUMIFS('Trading History'!$N$4:$N1003, 'Trading History'!$K$4:$K1003, CONCAT(">", $A43)) -> 290.89798 | E43: ST Units | F43: =IFERROR(SUMIFS('Trading History'!$R$4:$R1003, 'Trading History'!$O$4:$O1003, CONCAT(">", $A43)), 0) -> 290.89798 | H43: LT Units | I43: =SUMIFS('Trading History'!$V$4:$V1003, 'Trading History'!$S$4:$S1003, CONCAT(">", $A43)) -> 0 | K43: Units | L43: =SUMIFS('Trading History'!$AB$4:$AB1003, 'Trading History'!$Y$4:$Y1003, CONCAT(">", $A43)) -> 0
B44: Avg % | C44: =IFERROR(Index!C45/(Index!C43*Index!$J$1), 0) -> 0 | E44: ST Avg % | F44: =IFERROR(Index!F45/(Index!F43*Index!$J$1), 0) -> 0 | H44: LT Avg % | I44: =IFERROR(Index!I45/(Index!I43*Index!$J$1), 0) -> 0 | K44: Avg % | L44: =IFERROR(Index!L45/(Index!L43*Index!$J$1), 0) -> 0
B45: Gain | C45: =SUMIFS('Trading History'!$L$4:$L1003, 'Trading History'!$K$4:$K1003, CONCAT(">", $A43)) -> 5795.4442 | E45: ST Gain | F45: =SUMIFS('Trading History'!$P$4:$P1003, 'Trading History'!$O$4:$O1003, CONCAT(">", $A43)) -> 5795.4442 | H45: LT Gain | I45: =SUMIFS('Trading History'!$T$4:$T1003, 'Trading History'!$S$4:$S1003, CONCAT(">", $A43)) -> 0 | K45: Gain | L45: =SUMIFS('Trading History'!$Z$4:$Z1003, 'Trading History'!$Y$4:$Y1003, CONCAT(">", $A43)) -> 0
B46: Invested | C46: =Index!C47-Index!C45 -> 4999.78 | E46: ST Invested | F46: =Index!F47-Index!F45 -> 4999.78 | H46: LT Invested | I46: =Index!I47-Index!I45 -> 0 | K46: Invested | L46: =Index!L47-Index!L45 -> 0
B47: Gross | C47: =SUMIFS('Trading History'!$M$4:$M1003, 'Trading History'!$K$4:$K1003, CONCAT(">", $A43)) -> 10795.224 | E47: ST Gross | F47: =SUMIFS('Trading History'!$Q$4:$Q1003, 'Trading History'!$O$4:$O1003, CONCAT(">", $A43)) -> 10795.224 | H47: LT Gross | I47: =SUMIFS('Trading History'!$U$4:$U1003, 'Trading History'!$S$4:$S1003, CONCAT(">", $A43)) -> 0 | K47: Gross | L47: =SUMIFS('Trading History'!$AA$4:$AA1003, 'Trading History'!$Y$4:$Y1003, CONCAT(">", $A43)) -> 0
A50: 0.25 | B50: Units | C50: =SUMIFS('Trading History'!$N$4:$N1003, 'Trading History'!$K$4:$K1003, CONCAT(">", $A50)) -> 290.89798 | E50: ST Units | F50: =IFERROR(SUMIFS('Trading History'!$R$4:$R1003, 'Trading History'!$O$4:$O1003, CONCAT(">", $A50)), 0) -> 290.89798 | H50: LT Units | I50: =SUMIFS('Trading History'!$V$4:$V1003, 'Trading History'!$S$4:$S1003, CONCAT(">", $A50)) -> 0 | K50: Units | L50: =SUMIFS('Trading History'!$AB$4:$AB1003, 'Trading History'!$Y$4:$Y1003, CONCAT(">", $A50)) -> 0
B51: Avg % | C51: =IFERROR(Index!C52/(Index!C50*Index!$J$1), 0) -> 0 | E51: ST Avg % | F51: =IFERROR(Index!F52/(Index!F50*Index!$J$1), 0) -> 0 | H51: LT Avg % | I51: =IFERROR(Index!I52/(Index!I50*Index!$J$1), 0) -> 0 | K51: Avg % | L51: =IFERROR(Index!L52/(Index!L50*Index!$J$1), 0) -> 0
B52: Gain | C52: =SUMIFS('Trading History'!$L$4:$L1003, 'Trading History'!$K$4:$K1003, CONCAT(">", $A50)) -> 5795.4442 | E52: ST Gain | F52: =SUMIFS('Trading History'!$P$4:$P1003, 'Trading History'!$O$4:$O1003, CONCAT(">", $A50)) -> 5795.4442 | H52: LT Gain | I52: =SUMIFS('Trading History'!$T$4:$T1003, 'Trading History'!$S$4:$S1003, CONCAT(">", $A50)) -> 0 | K52: Gain | L52: =SUMIFS('Trading History'!$Z$4:$Z1003, 'Trading History'!$Y$4:$Y1003, CONCAT(">", $A50)) -> 0
B53: Invested | C53: =Index!C54-Index!C52 -> 4999.78 | E53: ST Invested | F53: =Index!F54-Index!F52 -> 4999.78 | H53: LT Invested | I53: =Index!I54-Index!I52 -> 0 | K53: Invested | L53: =Index!L54-Index!L52 -> 0
B54: Gross | C54: =SUMIFS('Trading History'!$M$4:$M1003, 'Trading History'!$K$4:$K1003, CONCAT(">", $A50)) -> 10795.224 | E54: ST Gross | F54: =SUMIFS('Trading History'!$Q$4:$Q1003, 'Trading History'!$O$4:$O1003, CONCAT(">", $A50)) -> 10795.224 | H54: LT Gross | I54: =SUMIFS('Trading History'!$U$4:$U1003, 'Trading History'!$S$4:$S1003, CONCAT(">", $A50)) -> 0 | K54: Gross | L54: =SUMIFS('Trading History'!$AA$4:$AA1003, 'Trading History'!$Y$4:$Y1003, CONCAT(">", $A50)) -> 0
A57: 0.2 | B57: Units | C57: =SUMIFS('Trading History'!$N$4:$N1003, 'Trading History'!$K$4:$K1003, CONCAT(">", $A57)) -> 290.89798 | E57: ST Units | F57: =IFERROR(SUMIFS('Trading History'!$R$4:$R1003, 'Trading History'!$O$4:$O1003, CONCAT(">", $A57)), 0) -> 290.89798 | H57: LT Units | I57: =SUMIFS('Trading History'!$V$4:$V1003, 'Trading History'!$S$4:$S1003, CONCAT(">", $A57)) -> 0 | K57: Units | L57: =SUMIFS('Trading History'!$AB$4:$AB1003, 'Trading History'!$Y$4:$Y1003, CONCAT(">", $A57)) -> 0
B58: Avg % | C58: =IFERROR(Index!C59/(Index!C57*Index!$J$1), 0) -> 0 | E58: ST Avg % | F58: =IFERROR(Index!F59/(Index!F57*Index!$J$1), 0) -> 0 | H58: LT Avg % | I58: =IFERROR(Index!I59/(Index!I57*Index!$J$1), 0) -> 0 | K58: Avg % | L58: =IFERROR(Index!L59/(Index!L57*Index!$J$1), 0) -> 0
B59: Gain | C59: =SUMIFS('Trading History'!$L$4:$L1003, 'Trading History'!$K$4:$K1003, CONCAT(">", $A57)) -> 5795.4442 | E59: ST Gain | F59: =SUMIFS('Trading History'!$P$4:$P1003, 'Trading History'!$O$4:$O1003, CONCAT(">", $A57)) -> 5795.4442 | H59: LT Gain | I59: =SUMIFS('Trading History'!$T$4:$T1003, 'Trading History'!$S$4:$S1003, CONCAT(">", $A57)) -> 0 | K59: Gain | L59: =SUMIFS('Trading History'!$Z$4:$Z1003, 'Trading History'!$Y$4:$Y1003, CONCAT(">", $A57)) -> 0
B60: Invested | C60: =Index!C61-Index!C59 -> 4999.78 | E60: ST Invested | F60: =Index!F61-Index!F59 -> 4999.78 | H60: LT Invested | I60: =Index!I61-Index!I59 -> 0 | K60: Invested | L60: =Index!L61-Index!L59 -> 0
B61: Gross | C61: =SUMIFS('Trading History'!$M$4:$M1003, 'Trading History'!$K$4:$K1003, CONCAT(">", $A57)) -> 10795.224 | E61: ST Gross | F61: =SUMIFS('Trading History'!$Q$4:$Q1003, 'Trading History'!$O$4:$O1003, CONCAT(">", $A57)) -> 10795.224 | H61: LT Gross | I61: =SUMIFS('Trading History'!$U$4:$U1003, 'Trading History'!$S$4:$S1003, CONCAT(">", $A57)) -> 0 | K61: Gross | L61: =SUMIFS('Trading History'!$AA$4:$AA1003, 'Trading History'!$Y$4:$Y1003, CONCAT(">", $A57)) -> 0
A64: 0.15 | B64: Units | C64: =SUMIFS('Trading History'!$N$4:$N1003, 'Trading History'!$K$4:$K1003, CONCAT(">", $A64)) -> 290.89798 | E64: ST Units | F64: =IFERROR(SUMIFS('Trading History'!$R$4:$R1003, 'Trading History'!$O$4:$O1003, CONCAT(">", $A64)), 0) -> 290.89798 | H64: LT Units | I64: =SUMIFS('Trading History'!$V$4:$V1003, 'Trading History'!$S$4:$S1003, CONCAT(">", $A64)) -> 0 | K64: Units | L64: =SUMIFS('Trading History'!$AB$4:$AB1003, 'Trading History'!$Y$4:$Y1003, CONCAT(">", $A64)) -> 0
B65: Avg % | C65: =IFERROR(Index!C66/(Index!C64*Index!$J$1), 0) -> 0 | E65: ST Avg % | F65: =IFERROR(Index!F66/(Index!F64*Index!$J$1), 0) -> 0 | H65: LT Avg % | I65: =IFERROR(Index!I66/(Index!I64*Index!$J$1), 0) -> 0 | K65: Avg % | L65: =IFERROR(Index!L66/(Index!L64*Index!$J$1), 0) -> 0
B66: Gain | C66: =SUMIFS('Trading History'!$L$4:$L1003, 'Trading History'!$K$4:$K1003, CONCAT(">", $A64)) -> 5795.4442 | E66: ST Gain | F66: =SUMIFS('Trading History'!$P$4:$P1003, 'Trading History'!$O$4:$O1003, CONCAT(">", $A64)) -> 5795.4442 | H66: LT Gain | I66: =SUMIFS('Trading History'!$T$4:$T1003, 'Trading History'!$S$4:$S1003, CONCAT(">", $A64)) -> 0 | K66: Gain | L66: =SUMIFS('Trading History'!$Z$4:$Z1003, 'Trading History'!$Y$4:$Y1003, CONCAT(">", $A64)) -> 0
B67: Invested | C67: =Index!C68-Index!C66 -> 4999.78 | E67: ST Invested | F67: =Index!F68-Index!F66 -> 4999.78 | H67: LT Invested | I67: =Index!I68-Index!I66 -> 0 | K67: Invested | L67: =Index!L68-Index!L66 -> 0
B68: Gross | C68: =SUMIFS('Trading History'!$M$4:$M1003, 'Trading History'!$K$4:$K1003, CONCAT(">", $A64)) -> 10795.224 | E68: ST Gross | F68: =SUMIFS('Trading History'!$Q$4:$Q1003, 'Trading History'!$O$4:$O1003, CONCAT(">", $A64)) -> 10795.224 | H68: LT Gross | I68: =SUMIFS('Trading History'!$U$4:$U1003, 'Trading History'!$S$4:$S1003, CONCAT(">", $A64)) -> 0 | K68: Gross | L68: =SUMIFS('Trading History'!$AA$4:$AA1003, 'Trading History'!$Y$4:$Y1003, CONCAT(">", $A64)) -> 0
A71: 0.1 | B71: Units | C71: =SUMIFS('Trading History'!$N$4:$N1003, 'Trading History'!$K$4:$K1003, CONCAT(">", $A71)) -> 290.89798 | E71: ST Units | F71: =IFERROR(SUMIFS('Trading History'!$R$4:$R1003, 'Trading History'!$O$4:$O1003, CONCAT(">", $A71)), 0) -> 290.89798 | H71: LT Units | I71: =SUMIFS('Trading History'!$V$4:$V1003, 'Trading History'!$S$4:$S1003, CONCAT(">", $A71)) -> 0 | K71: Units | L71: =SUMIFS('Trading History'!$AB$4:$AB1003, 'Trading History'!$Y$4:$Y1003, CONCAT(">", $A71)) -> 0
B72: Avg % | C72: =IFERROR(Index!C73/(Index!C71*Index!$J$1), 0) -> 0 | E72: ST Avg % | F72: =IFERROR(Index!F73/(Index!F71*Index!$J$1), 0) -> 0 | H72: LT Avg % | I72: =IFERROR(Index!I73/(Index!I71*Index!$J$1), 0) -> 0 | K72: Avg % | L72: =IFERROR(Index!L73/(Index!L71*Index!$J$1), 0) -> 0
B73: Gain | C73: =SUMIFS('Trading History'!$L$4:$L1003, 'Trading History'!$K$4:$K1003, CONCAT(">", $A71)) -> 5795.4442 | E73: ST Gain | F73: =SUMIFS('Trading History'!$P$4:$P1003, 'Trading History'!$O$4:$O1003, CONCAT(">", $A71)) -> 5795.4442 | H73: LT Gain | I73: =SUMIFS('Trading History'!$T$4:$T1003, 'Trading History'!$S$4:$S1003, CONCAT(">", $A71)) -> 0 | K73: Gain | L73: =SUMIFS('Trading History'!$Z$4:$Z1003, 'Trading History'!$Y$4:$Y1003, CONCAT(">", $A71)) -> 0
B74: Invested | C74: =Index!C75-Index!C73 -> 4999.78 | E74: ST Invested | F74: =Index!F75-Index!F73 -> 4999.78 | H74: LT Invested | I74: =Index!I75-Index!I73 -> 0 | K74: Invested | L74: =Index!L75-Index!L73 -> 0
B75: Gross | C75: =SUMIFS('Trading History'!$M$4:$M1003, 'Trading History'!$K$4:$K1003, CONCAT(">", $A71)) -> 10795.224 | E75: ST Gross | F75: =SUMIFS('Trading History'!$Q$4:$Q1003, 'Trading History'!$O$4:$O1003, CONCAT(">", $A71)) -> 10795.224 | H75: LT Gross | I75: =SUMIFS('Trading History'!$U$4:$U1003, 'Trading History'!$S$4:$S1003, CONCAT(">", $A71)) -> 0 | K75: Gross | L75: =SUMIFS('Trading History'!$AA$4:$AA1003, 'Trading History'!$Y$4:$Y1003, CONCAT(">", $A71)) -> 0
A78: 0.05 | B78: Units | C78: =SUMIFS('Trading History'!$N$4:$N1003, 'Trading History'!$K$4:$K1003, CONCAT(">", $A78)) -> 290.89798 | E78: ST Units | F78: =IFERROR(SUMIFS('Trading History'!$R$4:$R1003, 'Trading History'!$O$4:$O1003, CONCAT(">", $A78)), 0) -> 290.89798 | H78: LT Units | I78: =SUMIFS('Trading History'!$V$4:$V1003, 'Trading History'!$S$4:$S1003, CONCAT(">", $A78)) -> 0 | K78: Units | L78: =SUMIFS('Trading History'!$AB$4:$AB1003, 'Trading History'!$Y$4:$Y1003, CONCAT(">", $A78)) -> 0
B79: Avg % | C79: =IFERROR(Index!C80/(Index!C78*Index!$J$1), 0) -> 0 | E79: ST Avg % | F79: =IFERROR(Index!F80/(Index!F78*Index!$J$1), 0) -> 0 | H79: LT Avg % | I79: =IFERROR(Index!I80/(Index!I78*Index!$J$1), 0) -> 0 | K79: Avg % | L79: =IFERROR(Index!L80/(Index!L78*Index!$J$1), 0) -> 0
B80: Gain | C80: =SUMIFS('Trading History'!$L$4:$L1003, 'Trading History'!$K$4:$K1003, CONCAT(">", $A78)) -> 5795.4442 | E80: ST Gain | F80: =SUMIFS('Trading History'!$P$4:$P1003, 'Trading History'!$O$4:$O1003, CONCAT(">", $A78)) -> 5795.4442 | H80: LT Gain | I80: =SUMIFS('Trading History'!$T$4:$T1003, 'Trading History'!$S$4:$S1003, CONCAT(">", $A78)) -> 0 | K80: Gain | L80: =SUMIFS('Trading History'!$Z$4:$Z1003, 'Trading History'!$Y$4:$Y1003, CONCAT(">", $A78)) -> 0
B81: Invested | C81: =Index!C82-Index!C80 -> 4999.78 | E81: ST Invested | F81: =Index!F82-Index!F80 -> 4999.78 | H81: LT Invested | I81: =Index!I82-Index!I80 -> 0 | K81: Invested | L81: =Index!L82-Index!L80 -> 0
B82: Gross | C82: =SUMIFS('Trading History'!$M$4:$M1003, 'Trading History'!$K$4:$K1003, CONCAT(">", $A78)) -> 10795.224 | E82: ST Gross | F82: =SUMIFS('Trading History'!$Q$4:$Q1003, 'Trading History'!$O$4:$O1003, CONCAT(">", $A78)) -> 10795.224 | H82: LT Gross | I82: =SUMIFS('Trading History'!$U$4:$U1003, 'Trading History'!$S$4:$S1003, CONCAT(">", $A78)) -> 0 | K82: Gross | L82: =SUMIFS('Trading History'!$AA$4:$AA1003, 'Trading History'!$Y$4:$Y1003, CONCAT(">", $A78)) -> 0
A85: 0 | B85: Units | C85: =SUMIFS('Trading History'!$N$4:$N1003, 'Trading History'!$K$4:$K1003, CONCAT(">", $A85)) -> 290.89798 | E85: ST Units | F85: =IFERROR(SUMIFS('Trading History'!$R$4:$R1003, 'Trading History'!$O$4:$O1003, CONCAT(">", $A85)), 0) -> 290.89798 | H85: LT Units | I85: =SUMIFS('Trading History'!$V$4:$V1003, 'Trading History'!$S$4:$S1003, CONCAT(">", $A85)) -> 0 | K85: Units | L85: =SUMIFS('Trading History'!$AB$4:$AB1003, 'Trading History'!$Y$4:$Y1003, CONCAT(">", $A85)) -> 0
B86: Avg % | C86: =IFERROR(Index!C87/(Index!C85*Index!$J$1), 0) -> 0 | E86: ST Avg % | F86: =IFERROR(Index!F87/(Index!F85*Index!$J$1), 0) -> 0 | H86: LT Avg % | I86: =IFERROR(Index!I87/(Index!I85*Index!$J$1), 0) -> 0 | K86: Avg % | L86: =IFERROR(Index!L87/(Index!L85*Index!$J$1), 0) -> 0
B87: Gain | C87: =SUMIFS('Trading History'!$L$4:$L1003, 'Trading History'!$K$4:$K1003, CONCAT(">", $A85)) -> 5795.4442 | E87: ST Gain | F87: =SUMIFS('Trading History'!$P$4:$P1003, 'Trading History'!$O$4:$O1003, CONCAT(">", $A85)) -> 5795.4442 | H87: LT Gain | I87: =SUMIFS('Trading History'!$T$4:$T1003, 'Trading History'!$S$4:$S1003, CONCAT(">", $A85)) -> 0 | K87: Gain | L87: =SUMIFS('Trading History'!$Z$4:$Z1003, 'Trading History'!$Y$4:$Y1003, CONCAT(">", $A85)) -> 0
B88: Invested | C88: =Index!C89-Index!C87 -> 4999.78 | E88: ST Invested | F88: =Index!F89-Index!F87 -> 4999.78 | H88: LT Invested | I88: =Index!I89-Index!I87 -> 0 | K88: Invested | L88: =Index!L89-Index!L87 -> 0
B89: Gross | C89: =SUMIFS('Trading History'!$M$4:$M1003, 'Trading History'!$K$4:$K1003, CONCAT(">", $A85)) -> 10795.224 | E89: ST Gross | F89: =SUMIFS('Trading History'!$Q$4:$Q1003, 'Trading History'!$O$4:$O1003, CONCAT(">", $A85)) -> 10795.224 | H89: LT Gross | I89: =SUMIFS('Trading History'!$U$4:$U1003, 'Trading History'!$S$4:$S1003, CONCAT(">", $A85)) -> 0 | K89: Gross | L89: =SUMIFS('Trading History'!$AA$4:$AA1003, 'Trading History'!$Y$4:$Y1003, CONCAT(">", $A85)) -> 0
